MANIFEST.in
description.rst
setup.py
paladin/__init__.py
paladin/__main__.py
paladin/action.py
paladin/bcolors.py
paladin/dependency.py
paladin/paladin.py
paladin/project.py
paladin.egg-info/PKG-INFO
paladin.egg-info/SOURCES.txt
paladin.egg-info/dependency_links.txt
paladin.egg-info/entry_points.txt
paladin.egg-info/top_level.txt