Metadata-Version: 1.0
Name: paladin
Version: 0.6.1
Summary: Android Dependency Manager for libraries that aren't packaged as .jar or .aar - Paladin fells your dependencies like a boss.
Home-page: http://jonathonstaff.com/paladin
Author: Jonathon Staff
Author-email: jon@nplexity.com
License: UNKNOWN
Platform: UNKNOWN
